<annotation>
	<folder>Images</folder>
	<filename>160.jpg</filename>
	<path>I:\DOTA_dataset\plane_data_2018_7_16\Images\160.jpg</path>
	<source>
		<database>Unknown</database>
	</source>
	<size>
		<width>768</width>
		<height>512</height>
		<depth>3</depth>
	</size>
	<segmented>0</segmented>
	<object>
		<name>KC-135</name>
		<pose>Unspecified</pose>
		<truncated>0</truncated>
		<difficult>0</difficult>
		<bndbox>
			<xmin>146</xmin>
			<ymin>81</ymin>
			<xmax>243</xmax>
			<ymax>171</ymax>
		</bndbox>
	</object>
	<object>
		<name>KC-135</name>
		<pose>Unspecified</pose>
		<truncated>0</truncated>
		<difficult>0</difficult>
		<bndbox>
			<xmin>121</xmin>
			<ymin>196</ymin>
			<xmax>217</xmax>
			<ymax>286</ymax>
		</bndbox>
	</object>
	<object>
		<name>KC-135</name>
		<pose>Unspecified</pose>
		<truncated>0</truncated>
		<difficult>0</difficult>
		<bndbox>
			<xmin>97</xmin>
			<ymin>309</ymin>
			<xmax>194</xmax>
			<ymax>403</ymax>
		</bndbox>
	</object>
	<object>
		<name>KC-135</name>
		<pose>Unspecified</pose>
		<truncated>0</truncated>
		<difficult>0</difficult>
		<bndbox>
			<xmin>307</xmin>
			<ymin>355</ymin>
			<xmax>402</xmax>
			<ymax>447</ymax>
		</bndbox>
	</object>
	<object>
		<name>KC-135</name>
		<pose>Unspecified</pose>
		<truncated>1</truncated>
		<difficult>0</difficult>
		<bndbox>
			<xmin>170</xmin>
			<ymin>1</ymin>
			<xmax>273</xmax>
			<ymax>49</ymax>
		</bndbox>
	</object>
</annotation>
