<annotation>
	<folder>Images</folder>
	<filename>193.jpg</filename>
	<path>F:\windows_v1.5.1\plane_data_2018_7_16\Images\193.jpg</path>
	<source>
		<database>Unknown</database>
	</source>
	<size>
		<width>768</width>
		<height>512</height>
		<depth>3</depth>
	</size>
	<segmented>0</segmented>
	<object>
		<name>plane</name>
		<pose>Unspecified</pose>
		<truncated>0</truncated>
		<difficult>0</difficult>
		<bndbox>
			<xmin>398</xmin>
			<ymin>232</ymin>
			<xmax>465</xmax>
			<ymax>288</ymax>
		</bndbox>
	</object>
	<object>
		<name>plane</name>
		<pose>Unspecified</pose>
		<truncated>0</truncated>
		<difficult>0</difficult>
		<bndbox>
			<xmin>397</xmin>
			<ymin>431</ymin>
			<xmax>470</xmax>
			<ymax>490</ymax>
		</bndbox>
	</object>
	<object>
		<name>plane</name>
		<pose>Unspecified</pose>
		<truncated>0</truncated>
		<difficult>0</difficult>
		<bndbox>
			<xmin>191</xmin>
			<ymin>364</ymin>
			<xmax>256</xmax>
			<ymax>424</ymax>
		</bndbox>
	</object>
	<object>
		<name>plane</name>
		<pose>Unspecified</pose>
		<truncated>0</truncated>
		<difficult>0</difficult>
		<bndbox>
			<xmin>190</xmin>
			<ymin>431</ymin>
			<xmax>259</xmax>
			<ymax>491</ymax>
		</bndbox>
	</object>
	<object>
		<name>plane</name>
		<pose>Unspecified</pose>
		<truncated>1</truncated>
		<difficult>0</difficult>
		<bndbox>
			<xmin>1</xmin>
			<ymin>230</ymin>
			<xmax>46</xmax>
			<ymax>291</ymax>
		</bndbox>
	</object>
	<object>
		<name>plane</name>
		<pose>Unspecified</pose>
		<truncated>0</truncated>
		<difficult>0</difficult>
		<bndbox>
			<xmin>3</xmin>
			<ymin>427</ymin>
			<xmax>46</xmax>
			<ymax>488</ymax>
		</bndbox>
	</object>
</annotation>
