<annotation>
	<folder>Images</folder>
	<filename>455.jpg</filename>
	<path>F:\windows_v1.5.1\plane_data_2018_7_16\Images\455.jpg</path>
	<source>
		<database>Unknown</database>
	</source>
	<size>
		<width>939</width>
		<height>305</height>
		<depth>3</depth>
	</size>
	<segmented>0</segmented>
	<object>
		<name>C-17</name>
		<pose>Unspecified</pose>
		<truncated>0</truncated>
		<difficult>0</difficult>
		<bndbox>
			<xmin>7</xmin>
			<ymin>151</ymin>
			<xmax>119</xmax>
			<ymax>251</ymax>
		</bndbox>
	</object>
	<object>
		<name>C-17</name>
		<pose>Unspecified</pose>
		<truncated>0</truncated>
		<difficult>0</difficult>
		<bndbox>
			<xmin>188</xmin>
			<ymin>126</ymin>
			<xmax>302</xmax>
			<ymax>226</ymax>
		</bndbox>
	</object>
	<object>
		<name>C-17</name>
		<pose>Unspecified</pose>
		<truncated>0</truncated>
		<difficult>0</difficult>
		<bndbox>
			<xmin>343</xmin>
			<ymin>107</ymin>
			<xmax>449</xmax>
			<ymax>200</ymax>
		</bndbox>
	</object>
	<object>
		<name>KC-135</name>
		<pose>Unspecified</pose>
		<truncated>0</truncated>
		<difficult>0</difficult>
		<bndbox>
			<xmin>525</xmin>
			<ymin>111</ymin>
			<xmax>610</xmax>
			<ymax>186</ymax>
		</bndbox>
	</object>
	<object>
		<name>KC-135</name>
		<pose>Unspecified</pose>
		<truncated>0</truncated>
		<difficult>0</difficult>
		<bndbox>
			<xmin>807</xmin>
			<ymin>72</ymin>
			<xmax>888</xmax>
			<ymax>145</ymax>
		</bndbox>
	</object>
</annotation>
